pump_swap/__init__.py
pump_swap/pump_swap.py
pump_swap/pump_utils.py
pump_swap-0.7.0.dist-info/METADATA
pump_swap-0.7.0.dist-info/WHEEL
pump_swap-0.7.0.dist-info/top_level.txt
pump_swap-0.7.0.dist-info/RECORD
