Metadata-Version: 2.1
Name: pump_swap
Version: 0.7.0
Summary: A Python module for interacting with Solana's Pump.fun tokens
Home-page: https://github.com/FLOCK4H/pump_swap
Author: Flock4h
Author-email: flock4h@gmail.com
Classifier: Programming Language :: Python :: 3.8
Classifier: License :: OSI Approved :: MIT License
Classifier: Operating System :: OS Independent
Classifier: Topic :: Software Development :: Libraries
Classifier: Topic :: Utilities
Requires-Python: >=3.8
Requires-Dist: solders>=0.21.0
Requires-Dist: solana>=0.35.1
Requires-Dist: borsh-construct
Requires-Dist: aiohttp
Requires-Dist: requests
